Hashings/__init__.py
Hashings/secure_random.py
cpstress-0.2.1.dist-info/licenses/LICENSE
cpstress-0.2.1.dist-info/METADATA
cpstress-0.2.1.dist-info/WHEEL
cpstress-0.2.1.dist-info/top_level.txt
cpstress-0.2.1.dist-info/RECORD
