Metadata-Version: 2.4
Name: cpstress
Version: 0.2.1
Summary: Cryptographically secure stress testing data generator library for competitive programming. Generates random test cases for arrays, numbers, strings, and graphs using secrets module.
Home-page: https://github.com/sharpsalt/cpstress
Author: Srijan Verma
Author-email: srijan@example.com
Project-URL: Bug Reports, https://github.com/sharpsalt/cpstress/issues
Project-URL: Source, https://github.com/sharpsalt/cpstress
Keywords: competitive programming test data generation random stress-testing
Classifier: Programming Language :: Python :: 3
Classifier: Programming Language :: Python :: 3.7
Classifier: Programming Language :: Python :: 3.8
Classifier: Programming Language :: Python :: 3.9
Classifier: Programming Language :: Python :: 3.10
Classifier: Programming Language :: Python :: 3.11
Classifier: Operating System :: OS Independent
Classifier: Development Status :: 3 - Alpha
Classifier: Intended Audience :: Developers
Classifier: Topic :: Software Development :: Testing
Requires-Python: >=3.7
License-File: LICENSE
Dynamic: author
Dynamic: author-email
Dynamic: classifier
Dynamic: description
Dynamic: description-content-type
Dynamic: home-page
Dynamic: keywords
Dynamic: license-file
Dynamic: project-url
Dynamic: requires-python
Dynamic: summary
